Metadata-Version: 2.1
Name: libpythonpro-github
Version: 0.2
Summary: Módulo para exemplificar construção de projetos Python no curso PyTools
Home-page: https://github.com/guyrux/PyTools-API-GitHub
Author: Gustavo Suto
Author-email: guyrux@gmail.com
License: MIT License
